{
  "kind": "collectionType",
  "collectionName": "pianos",
  "info": {
    "singularName": "piano",
    "pluralName": "pianos",
    "displayName": "Pianos"
  },
  "options": {
    "draftAndPublish": true
  },
  "pluginOptions": {},
  "attributes": {
    "name": {
      "type": "string",
      "required": true
    },
    "description": {
      "type": "richtext"
    },
    "price": {
      "type": "integer"
    },
    "image": {
      "allowedTypes": [
        "images",
        "files",
        "videos",
        "audios"
      ],
      "type": "media",
      "multiple": false
    },
    "url": {
      "type": "uid",
      "targetField": "name"
    }
  }
}
